databackend/__init__.py
databackend/tests/a_data_class.py
databackend/tests/an_unimported_module.py
databackend/tests/test_databackend.py
databackend-0.0.2.dist-info/LICENSE
databackend-0.0.2.dist-info/METADATA
databackend-0.0.2.dist-info/WHEEL
databackend-0.0.2.dist-info/top_level.txt
databackend-0.0.2.dist-info/RECORD
