Metadata-Version: 2.1
Name: databackend
Version: 0.0.2
Summary: Abstract data dispatch
Home-page: https://github.com/machow/databackend
Author: Michael Chow
Author-email: mc_al_github@fastmail.com
License: MIT
Keywords: data
Classifier: Programming Language :: Python :: 3.7
Classifier: Programming Language :: Python :: 3.8
Classifier: Programming Language :: Python :: 3.9
Classifier: Programming Language :: Python :: 3.10
Requires-Python: >=3.7
License-File: LICENSE
Provides-Extra: dev
Requires-Dist: pip-tools; extra == "dev"
Requires-Dist: pytest; extra == "dev"
